gen_lsp_tdm/cmake_init.py
gen_lsp_tdm/main.py
gen_lsp_tdm/data/CMakeLists.txt
gen_lsp_tdm/data/CMakePresets.json
gen_lsp_tdm/data/Makefile
gen_lsp_tdm/gen_lsp_for_gcc/main.py
gen_lsp_tdm/gen_lsp_for_gcc/open_error_file.py
gen_lsp_tdm/gen_lsp_for_gcc/open_output_file.py
gen_lsp_tdm-2025.3.20.1.dist-info/METADATA
gen_lsp_tdm-2025.3.20.1.dist-info/WHEEL
gen_lsp_tdm-2025.3.20.1.dist-info/entry_points.txt
gen_lsp_tdm-2025.3.20.1.dist-info/licenses/LICENSE
gen_lsp_tdm-2025.3.20.1.dist-info/RECORD
