Metadata-Version: 2.4
Name: gen-lsp-tdm
Version: 2025.3.20.1
Summary: Fix compile commands for gcc/tdm-gcc for use with clangd on Windows
Project-URL: Repository, https://github.com/soda92/gen_lsp_tdm
License-File: LICENSE
Requires-Python: >=3.10
Requires-Dist: sodatools>=2025.2.16.0
